main.py
source_couchbase/__init__.py
source_couchbase/queries.py
source_couchbase/run.py
source_couchbase/source.py
source_couchbase/spec.yaml
source_couchbase/streams.py
airbyte_source_couchbase-0.1.8.dist-info/METADATA
airbyte_source_couchbase-0.1.8.dist-info/WHEEL
airbyte_source_couchbase-0.1.8.dist-info/entry_points.txt
airbyte_source_couchbase-0.1.8.dist-info/RECORD
