Metadata-Version: 2.3
Name: airbyte-source-couchbase
Version: 0.1.8
Summary: Source implementation for couchbase.
License: MIT
Author: Airbyte
Author-email: contact@airbyte.io
Requires-Python: >=3.10,<3.12
Classifier: License :: OSI Approved :: MIT License
Classifier: Programming Language :: Python :: 3
Classifier: Programming Language :: Python :: 3.10
Classifier: Programming Language :: Python :: 3.11
Requires-Dist: airbyte-cdk (>=5.13.0,<6.0.0)
Requires-Dist: couchbase (>=4.3.1,<5.0.0)
Requires-Dist: pendulum (==2.1.2)
Requires-Dist: requests (>=2.32.3,<3.0.0)
Project-URL: Documentation, https://docs.airbyte.com/integrations/sources/couchbase
Project-URL: Homepage, https://airbyte.com
Project-URL: Repository, https://github.com/airbytehq/airbyte
